yafowil.widget.wysihtml5-1.5-py3.9-nspkg.pth
yafowil/widget/wysihtml5/__init__.py
yafowil/widget/wysihtml5/example.py
yafowil/widget/wysihtml5/tests.py
yafowil/widget/wysihtml5/widget.py
yafowil/widget/wysihtml5/resources/widget.css
yafowil/widget/wysihtml5/resources/widget.js
yafowil/widget/wysihtml5/resources/bootstrap3-wysihtml5/LICENCE
yafowil/widget/wysihtml5/resources/bootstrap3-wysihtml5/bootstrap-wysihtml5.css
yafowil/widget/wysihtml5/resources/bootstrap3-wysihtml5/bootstrap3-wysihtml5.js
yafowil/widget/wysihtml5/resources/bootstrap3-wysihtml5/wysiwyg-color.css
yafowil/widget/wysihtml5/resources/bootstrap3-wysihtml5/locales/bootstrap-wysihtml5.ar-AR.js
yafowil/widget/wysihtml5/resources/bootstrap3-wysihtml5/locales/bootstrap-wysihtml5.bg-BG.js
yafowil/widget/wysihtml5/resources/bootstrap3-wysihtml5/locales/bootstrap-wysihtml5.ca-CT.js
yafowil/widget/wysihtml5/resources/bootstrap3-wysihtml5/locales/bootstrap-wysihtml5.cs-CZ.js
yafowil/widget/wysihtml5/resources/bootstrap3-wysihtml5/locales/bootstrap-wysihtml5.da-DK.js
yafowil/widget/wysihtml5/resources/bootstrap3-wysihtml5/locales/bootstrap-wysihtml5.de-DE.js
yafowil/widget/wysihtml5/resources/bootstrap3-wysihtml5/locales/bootstrap-wysihtml5.el-GR.js
yafowil/widget/wysihtml5/resources/bootstrap3-wysihtml5/locales/bootstrap-wysihtml5.es-AR.js
yafowil/widget/wysihtml5/resources/bootstrap3-wysihtml5/locales/bootstrap-wysihtml5.es-ES.js
yafowil/widget/wysihtml5/resources/bootstrap3-wysihtml5/locales/bootstrap-wysihtml5.fr-FR.js
yafowil/widget/wysihtml5/resources/bootstrap3-wysihtml5/locales/bootstrap-wysihtml5.hr-HR.js
yafowil/widget/wysihtml5/resources/bootstrap3-wysihtml5/locales/bootstrap-wysihtml5.it-IT.js
yafowil/widget/wysihtml5/resources/bootstrap3-wysihtml5/locales/bootstrap-wysihtml5.ja-JP.js
yafowil/widget/wysihtml5/resources/bootstrap3-wysihtml5/locales/bootstrap-wysihtml5.ko-KR.js
yafowil/widget/wysihtml5/resources/bootstrap3-wysihtml5/locales/bootstrap-wysihtml5.lt-LT.js
yafowil_widget_wysihtml5-1.5.dist-info/licenses/LICENSE.rst
yafowil_widget_wysihtml5-1.5.dist-info/METADATA
yafowil_widget_wysihtml5-1.5.dist-info/WHEEL
yafowil_widget_wysihtml5-1.5.dist-info/entry_points.txt
yafowil_widget_wysihtml5-1.5.dist-info/namespace_packages.txt
yafowil_widget_wysihtml5-1.5.dist-info/top_level.txt
yafowil_widget_wysihtml5-1.5.dist-info/RECORD
